pydoca/__init__.py
pydoca/aggregate_root.py
pydoca/bootstrap.py
pydoca/entity.py
pydoca/event.py
pydoca/port_adapter.py
pydoca/py.typed
pydoca/repository.py
pydoca/unit_of_work.py
pydoca/use_case.py
pydoca/utils.py
pydoca/value_object.py
pydoca-1.0.0a0.dist-info/METADATA
pydoca-1.0.0a0.dist-info/WHEEL
pydoca-1.0.0a0.dist-info/licenses/LICENSE
pydoca-1.0.0a0.dist-info/RECORD
