Metadata-Version: 2.1
Name: pydoca
Version: 1.0.0a0
Summary: Domain-Oriented Clean Architecture Python library.
Project-URL: Homepage, https://github.com/jc-rosier/pydoca
Project-URL: Repository, https://github.com/jc-rosier/pydoca
Author-email: Jean-Christophe Rosier <jean-christophe.rosier@outlook.com>
License: The MIT License (MIT)
License-File: LICENSE
Classifier: Development Status :: 3 - Alpha
Classifier: Framework :: Pydantic
Classifier: Intended Audience :: Developers
Classifier: Intended Audience :: Information Technology
Classifier: Intended Audience :: System Administrators
Classifier: License :: OSI Approved :: MIT License
Classifier: Operating System :: OS Independent
Classifier: Programming Language :: Python
Classifier: Programming Language :: Python :: 3
Classifier: Programming Language :: Python :: 3 :: Only
Classifier: Programming Language :: Python :: 3.10
Classifier: Programming Language :: Python :: 3.11
Classifier: Programming Language :: Python :: 3.12
Classifier: Topic :: Internet
Classifier: Topic :: Software Development
Classifier: Topic :: Software Development :: Libraries
Classifier: Topic :: Software Development :: Libraries :: Application Frameworks
Classifier: Topic :: Software Development :: Libraries :: Python Modules
Classifier: Typing :: Typed
Requires-Python: >=3.11
Requires-Dist: pydantic
Provides-Extra: lint
Requires-Dist: black; extra == 'lint'
Requires-Dist: mypy; extra == 'lint'
Requires-Dist: pre-commit; extra == 'lint'
Requires-Dist: ruff; extra == 'lint'
Provides-Extra: test
Requires-Dist: coverage[toml]; extra == 'test'
Requires-Dist: fastapi; extra == 'test'
Requires-Dist: pytest; extra == 'test'
Requires-Dist: requests; extra == 'test'
Requires-Dist: uvicorn; extra == 'test'
